utmos/__init__.py
utmos/cli.py
utmos/gui.py
utmos/lightning_module.py
utmos/model.py
utmos/score.old.py
utmos/score.py
utmos-1.1.10.dist-info/LICENSE
utmos-1.1.10.dist-info/METADATA
utmos-1.1.10.dist-info/WHEEL
utmos-1.1.10.dist-info/entry_points.txt
utmos-1.1.10.dist-info/top_level.txt
utmos-1.1.10.dist-info/RECORD
