Metadata-Version: 2.1
Name: utmos
Version: 1.1.10
Summary: UT-Sarulab MOS prediction system using SSL models
Home-page: https://github.com/ttseval/utmos
Author: mrfakename
Author-email: me@mrfake.name
License: MIT
License-File: LICENSE
Requires-Dist: numpy
Requires-Dist: fairseq
Requires-Dist: cached-path
Requires-Dist: click
Requires-Dist: torchaudio
Requires-Dist: pytorch-lightning
Requires-Dist: transformers
